setup.py
salure_helpers/elastic/__init__.py
salure_helpers/elastic/elastic.py
salure_helpers_elastic.egg-info/PKG-INFO
salure_helpers_elastic.egg-info/SOURCES.txt
salure_helpers_elastic.egg-info/dependency_links.txt
salure_helpers_elastic.egg-info/not-zip-safe
salure_helpers_elastic.egg-info/requires.txt
salure_helpers_elastic.egg-info/top_level.txt