Metadata-Version: 1.0
Name: salure-helpers-elastic
Version: 0.0.2
Summary: elastic wrapper from Salure
Home-page: UNKNOWN
Author: D&A Salure
Author-email: support@salureconnnect.com
License: Salure License
Platform: UNKNOWN
